optrs_api-0.1.1.dist-info/METADATA
optrs_api-0.1.1.dist-info/WHEEL
optrs/__init__.py
optrs/optrs.cpython-39-x86_64-linux-gnu.so
optrs_api-0.1.1.dist-info/RECORD
