Metadata-Version: 2.1
Name: optrs-api
Version: 0.1.1
Classifier: Programming Language :: Rust
Classifier: Programming Language :: Python :: Implementation :: CPython
Classifier: Programming Language :: Python :: Implementation :: PyPy
Requires-Dist: optrs
Author: Tom Young
Requires-Python: >=3.6
